{
  "fields": "[{\"analyzed\": false, \"count\": 0, \"aggregatable\": true, \"type\": \"string\", \"name\": \"beat.name\", \"searchable\": true, \"scripted\": false, \"indexed\": true, \"doc_values\": true}, {\"analyzed\": false, \"count\": 0, \"aggregatable\": true, \"type\": \"string\", \"name\": \"beat.hostname\", \"searchable\": true, \"scripted\": false, \"indexed\": true, \"doc_values\": true}, {\"analyzed\": false, \"count\": 0, \"aggregatable\": true, \"type\": \"string\", \"name\": \"beat.version\", \"searchable\": true, \"scripted\": false, \"indexed\": true, \"doc_values\": true}, {\"analyzed\": false, \"count\": 0, \"aggregatable\": true, \"type\": \"date\", \"name\": \"@timestamp\", \"searchable\": true, \"scripted\": false, \"indexed\": true, \"doc_values\": true}, {\"analyzed\": false, \"count\": 0, \"aggregatable\": true, \"type\": \"string\", \"name\": \"tags\", \"searchable\": true, \"scripted\": false, \"indexed\": true, \"doc_values\": true}, {\"analyzed\": false, \"count\": 0, \"aggregatable\": true, \"name\": \"fields\", \"searchable\": true, \"scripted\": false, \"indexed\": true, \"doc_values\": true}, {\"analyzed\": false, \"count\": 0, \"aggregatable\": true, \"type\": \"string\", \"name\": \"meta.cloud.provider\", \"searchable\": true, \"scripted\": false, \"indexed\": true, \"doc_values\": true}, {\"analyzed\": false, \"count\": 0, \"aggregatable\": true, \"type\": \"string\", \"name\": \"meta.cloud.instance_id\", \"searchable\": true, \"scripted\": false, \"indexed\": true, \"doc_values\": true}, {\"analyzed\": false, \"count\": 0, \"aggregatable\": true, \"type\": \"string\", \"name\": \"meta.cloud.machine_type\", \"searchable\": true, \"scripted\": false, \"indexed\": true, \"doc_values\": true}, {\"analyzed\": false, \"count\": 0, \"aggregatable\": true, \"type\": \"string\", \"name\": \"meta.cloud.availability_zone\", \"searchable\": true, \"scripted\": false, \"indexed\": true, \"doc_values\": true}, {\"analyzed\": false, \"count\": 0, \"aggregatable\": true, \"type\": \"string\", \"name\": \"meta.cloud.project_id\", \"searchable\": true, \"scripted\": false, \"indexed\": true, \"doc_values\": true}, {\"analyzed\": false, \"count\": 0, \"aggregatable\": true, \"type\": \"string\", \"name\": \"meta.cloud.region\", \"searchable\": true, \"scripted\": false, \"indexed\": true, \"doc_values\": true}, {\"analyzed\": false, \"count\": 0, \"aggregatable\": true, \"type\": \"number\", \"name\": \"counter\", \"searchable\": true, \"scripted\": false, \"indexed\": true, \"doc_values\": true}]",
  "fieldFormatMap": "{\"@timestamp\": {\"id\": \"date\"}}",
  "timeFieldName": "@timestamp",
  "title": "jsonbeat-*"
}